src/UILoader.py
src/__init__.py
src/u_logic.py
qt_uiloader-1.0.3.dist-info/METADATA
qt_uiloader-1.0.3.dist-info/WHEEL
qt_uiloader-1.0.3.dist-info/top_level.txt
qt_uiloader-1.0.3.dist-info/RECORD
