Metadata-Version: 2.2
Name: qt-UILoader
Version: 1.0.3
Summary: 只要一个ui文件，自动加载对应的逻辑类.
Home-page: https://github.com/xindong888999/qt-UILoader.git
Author: xindong888
Author-email: xindong888 <xindong888@163.com>
Project-URL: Homepage, https://github.com/xindong888999/qt-UILoader.git
Project-URL: Bug Tracker, https://github.com/xindong888999/qt-UILoader/issues
Classifier: Programming Language :: Python :: 3
Classifier: License :: OSI Approved :: MIT License
Classifier: Operating System :: OS Independent
Requires-Python: >=3.9
Dynamic: author
Dynamic: home-page
Dynamic: requires-python
